setup.py
zuckup/__init__.py
zuckup/connection.py
zuckup/credentials.py
zuckup/defaults.py
zuckup/main.py
zuckup/parsers.py
zuckup/util.py
zuckup.egg-info/PKG-INFO
zuckup.egg-info/SOURCES.txt
zuckup.egg-info/dependency_links.txt
zuckup.egg-info/namespace_packages.txt
zuckup.egg-info/not-zip-safe
zuckup.egg-info/requires.txt
zuckup.egg-info/top_level.txt