Metadata-Version: 1.1
Name: zuckup
Version: 0.0.9
Summary: simple facebook parsing
Home-page: http://github.com/newslynx/zuckup
Author: Brian Abelson
Author-email: brian@newslynx.org
License: MIT
Platform: UNKNOWN
Classifier: Development Status :: 3 - Alpha
Classifier: Intended Audience :: Developers
Classifier: License :: OSI Approved :: MIT License
Classifier: Operating System :: OS Independent
Classifier: Programming Language :: Python
